drf_auth_jwt-1.1.0.dist-info/licenses/LICENSE
rest_framework_jwt/__init__.py
rest_framework_jwt/authentication.py
rest_framework_jwt/compat.py
rest_framework_jwt/models.py
rest_framework_jwt/serializers.py
rest_framework_jwt/settings.py
rest_framework_jwt/test.py
rest_framework_jwt/utils.py
rest_framework_jwt/views.py
rest_framework_jwt/locale/en_US/LC_MESSAGES/django.po
drf_auth_jwt-1.1.0.dist-info/METADATA
drf_auth_jwt-1.1.0.dist-info/WHEEL
drf_auth_jwt-1.1.0.dist-info/top_level.txt
drf_auth_jwt-1.1.0.dist-info/RECORD
